{"S1_Number_bins": [-0.5, 10.5, 11], "S1_Width_bins": [-0.01, 0.99, 40], "S1_Height_bins": [0, 10, 10], "S1_Energy_bins": [0, 50, 50], "S1_Charge_bins": [0, 2, 20], "S1_Time_bins": [0, 650, 650], "S2_Number_bins": [-0.5, 10.5, 11], "S2_Width_bins": [0, 50, 50], "S2_Height_bins": [0, 8000, 100], "S2_Energy_bins": [0, 20000.0, 100], "S2_Charge_bins": [0, 3500, 100], "S2_Time_bins": [640, 1300, 660], "S2_NSiPM_bins": [-0.5, 500.5, 501], "S2_IdSiPM_bins": [-0.5, 1792.5, 1793], "S2_QSiPM_bins": [0, 100, 100], "S2_XSiPM_bins": [-200, 200, 40], "S2_YSiPM_bins": [-200, 200, 40], "S1_Number_labels": ["S1 number (#)"], "S1_Width_labels": ["S1 width ($\\mu$s)"], "S1_Height_labels": ["S1 height (pes)"], "S1_Energy_labels": ["S1 energy (pes)"], "S1_Charge_labels": ["S1 charge (pes)"], "S1_Time_labels": ["S1 time ($\\mu$s)"], "S2_Number_labels": ["S2 number (#)"], "S2_Width_labels": ["S2 width ($\\mu$s)"], "S2_Height_labels": ["S2 height (pes)"], "S2_Energy_labels": ["S2 energy (pes)"], "S2_Charge_labels": ["S2 charge (pes)"], "S2_Time_labels": ["S2 time ($\\mu$s)"], "S2_NSiPM_labels": ["SiPM number (#)"], "S2_IdSiPM_labels": ["SiPM id"], "S2_QSiPM_labels": ["SiPM charge (pes)"], "S2_XSiPM_labels": ["X (mm)"], "S2_YSiPM_labels": ["Y (mm)"], "nPMT": 12}